py_valid_proxy/__init__.py
py_valid_proxy/__main__.py
py_valid_proxy/data/GeoLite2-Country.mmdb
py_valid_proxy/main.py
py_valid_proxy/valid_proxy.py
py_valid_proxy-0.3.1.dist-info/METADATA
py_valid_proxy-0.3.1.dist-info/WHEEL
py_valid_proxy-0.3.1.dist-info/entry_points.txt
py_valid_proxy-0.3.1.dist-info/RECORD
