Metadata-Version: 2.1
Name: py-valid-proxy
Version: 0.3.1
Summary: Valid proxy server ('alive' or 'dead')
Home-page: https://github.com/suvorinov/py_valid_proxy.git
Author: Suvorinov Oleg
Author-email: suvorinovoleg@yandex.ru
Requires-Python: >=3.8,<4.0
Classifier: Programming Language :: Python :: 3
Classifier: Programming Language :: Python :: 3.8
Classifier: Programming Language :: Python :: 3.9
Classifier: Programming Language :: Python :: 3.10
Classifier: Programming Language :: Python :: 3.11
Requires-Dist: dataclasses-json (>=0.6.3,<0.7.0)
Requires-Dist: geoip2 (>=4.7.0,<5.0.0)
Requires-Dist: requests (>=2.31.0,<3.0.0)
Requires-Dist: rich (>=13.7.0,<14.0.0)
